big_file_sort/__init__.py
big_file_sort-0.1.0.dist-info/DESCRIPTION.rst
big_file_sort-0.1.0.dist-info/METADATA
big_file_sort-0.1.0.dist-info/metadata.json
big_file_sort-0.1.0.dist-info/pbr.json
big_file_sort-0.1.0.dist-info/RECORD
big_file_sort-0.1.0.dist-info/top_level.txt
big_file_sort-0.1.0.dist-info/WHEEL
